read_only_admin/__init__.py
read_only_admin/admin.py
read_only_admin/apps.py
read_only_admin/conf.py
read_only_admin/models.py
read_only_admin/signals.py
read_only_admin/utils.py
read_only_admin/locale/en/LC_MESSAGES/django.mo
read_only_admin/locale/en/LC_MESSAGES/django.po
read_only_admin/locale/uk/LC_MESSAGES/django.mo
read_only_admin/locale/uk/LC_MESSAGES/django.po
read_only_admin/templates/admin/pagination.html
read_only_admin/templates/read_only_admin/change_form.html
read_only_admin/templates/read_only_admin/includes/fieldset.html
read_only_admin/templatetags/__init__.py
read_only_admin/templatetags/read_only_admin_tags.py
django_read_only_admin-0.17.5.dist-info/METADATA
django_read_only_admin-0.17.5.dist-info/MIT-LICENSE
django_read_only_admin-0.17.5.dist-info/WHEEL
django_read_only_admin-0.17.5.dist-info/top_level.txt
django_read_only_admin-0.17.5.dist-info/RECORD
