Metadata-Version: 2.1
Name: django-read-only-admin
Version: 0.17.5
Summary: Really full Django read only admin implementation
Home-page: https://github.com/vint21h/django-read-only-admin/
Author: Alexei Andrushievich
Author-email: vint21h@vint21h.pp.ua
License: MIT
Keywords: django,django-admin,admin,read-only
Platform: UNKNOWN
Classifier: Development Status :: 5 - Production/Stable
Classifier: Environment :: Plugins
Classifier: Framework :: Django :: 2.2
Classifier: Framework :: Django :: 3.2
Classifier: Framework :: Django :: 4.0
Classifier: License :: OSI Approved :: MIT License
Classifier: Operating System :: Unix
Classifier: Programming Language :: Python :: 3.7
Classifier: Programming Language :: Python :: 3.8
Classifier: Programming Language :: Python :: 3.9
Classifier: Programming Language :: Python :: 3.10
Classifier: Topic :: Utilities
License-File: MIT-LICENSE
Requires-Dist: django (<4.1,>=2.2)
Requires-Dist: django-appconf (>=1.0.3)
Provides-Extra: test
Requires-Dist: attrs (==21.4.0) ; extra == 'test'
Requires-Dist: bandit (==1.7.2) ; extra == 'test'
Requires-Dist: black (==22.1.0) ; extra == 'test'
Requires-Dist: bpython (==0.22.1) ; extra == 'test'
Requires-Dist: check-manifest (==0.47) ; extra == 'test'
Requires-Dist: check-wheel-contents (==0.3.4) ; extra == 'test'
Requires-Dist: coverage (==6.3.1) ; extra == 'test'
Requires-Dist: coveralls (==3.3.1) ; extra == 'test'
Requires-Dist: curlylint (==0.13.0) ; extra == 'test'
Requires-Dist: darglint (==1.8.1) ; extra == 'test'
Requires-Dist: dennis (==0.9) ; extra == 'test'
Requires-Dist: django-stubs (==1.9.0) ; extra == 'test'
Requires-Dist: dlint (==0.12.0) ; extra == 'test'
Requires-Dist: dodgy (==0.2.1) ; extra == 'test'
Requires-Dist: dotenv-linter (==0.3.0) ; extra == 'test'
Requires-Dist: flake8-annotations-complexity (==0.0.6) ; extra == 'test'
Requires-Dist: flake8-annotations-coverage (==0.0.5) ; extra == 'test'
Requires-Dist: flake8-broken-line (==0.4.0) ; extra == 'test'
Requires-Dist: flake8-bugbear (==22.1.11) ; extra == 'test'
Requires-Dist: flake8-builtins (==1.5.3) ; extra == 'test'
Requires-Dist: flake8-coding (==1.3.2) ; extra == 'test'
Requires-Dist: flake8-cognitive-complexity (==0.1.0) ; extra == 'test'
Requires-Dist: flake8-comprehensions (==3.8.0) ; extra == 'test'
Requires-Dist: flake8-debugger (==4.0.0) ; extra == 'test'
Requires-Dist: flake8-django (==1.1.2) ; extra == 'test'
Requires-Dist: flake8-docstrings (==1.6.0) ; extra == 'test'
Requires-Dist: flake8-eradicate (==1.2.0) ; extra == 'test'
Requires-Dist: flake8-executable (==2.1.1) ; extra == 'test'
Requires-Dist: flake8-expression-complexity (==0.0.9) ; extra == 'test'
Requires-Dist: flake8-fixme (==1.1.1) ; extra == 'test'
Requires-Dist: flake8-functions (==0.0.6) ; extra == 'test'
Requires-Dist: flake8-mutable (==1.2.0) ; extra == 'test'
Requires-Dist: flake8-no-implicit-concat (==0.3.3) ; extra == 'test'
Requires-Dist: flake8-print (==4.0.0) ; extra == 'test'
Requires-Dist: flake8-return (==1.1.3) ; extra == 'test'
Requires-Dist: flake8-simplify (==0.17.1) ; extra == 'test'
Requires-Dist: flake8-typing-imports (==1.12.0) ; extra == 'test'
Requires-Dist: flake8-use-fstring (==1.3) ; extra == 'test'
Requires-Dist: flake8-variables-names (==0.0.4) ; extra == 'test'
Requires-Dist: flake8 (==3.9.2) ; extra == 'test'
Requires-Dist: importlib-metadata (==4.11.1) ; extra == 'test'
Requires-Dist: interrogate (==1.5.0) ; extra == 'test'
Requires-Dist: isort (==5.10.1) ; extra == 'test'
Requires-Dist: mypy (==0.931) ; extra == 'test'
Requires-Dist: pep8-naming (==0.12.1) ; extra == 'test'
Requires-Dist: pip-outdated (==0.5.0) ; extra == 'test'
Requires-Dist: polint (==0.4) ; extra == 'test'
Requires-Dist: pre-commit-hooks (==4.1.0) ; extra == 'test'
Requires-Dist: pre-commit (==2.17.0) ; extra == 'test'
Requires-Dist: pygments (==2.11.2) ; extra == 'test'
Requires-Dist: pylint-django (==2.5.2) ; extra == 'test'
Requires-Dist: pylint (==2.12.2) ; extra == 'test'
Requires-Dist: pyroma (==3.2) ; extra == 'test'
Requires-Dist: pytest-cov (==3.0.0) ; extra == 'test'
Requires-Dist: pytest-django (==4.5.2) ; extra == 'test'
Requires-Dist: pytest-extra-durations (==0.1.3) ; extra == 'test'
Requires-Dist: pytest-instafail (==0.4.2) ; extra == 'test'
Requires-Dist: pytest-sugar (==0.9.4) ; extra == 'test'
Requires-Dist: pytest-timer[termcolor] (==0.0.11) ; extra == 'test'
Requires-Dist: pytest (==7.0.1) ; extra == 'test'
Requires-Dist: readme-renderer (==32.0) ; extra == 'test'
Requires-Dist: removestar (==1.3.1) ; extra == 'test'
Requires-Dist: seed-isort-config (==2.2.0) ; extra == 'test'
Requires-Dist: tabulate (==0.8.9) ; extra == 'test'
Requires-Dist: tox-gh-actions (==2.9.1) ; extra == 'test'
Requires-Dist: tox-pyenv (==1.1.0) ; extra == 'test'
Requires-Dist: tox (==3.24.5) ; extra == 'test'
Requires-Dist: twine (==3.8.0) ; extra == 'test'
Requires-Dist: wheel (==0.37.1) ; extra == 'test'
Requires-Dist: yesqa (==1.3.0) ; extra == 'test'
